mothakes/__init__.py
mothakes/json_util.py
mothakes-0.0.3.dist-info/LICENSE
mothakes-0.0.3.dist-info/METADATA
mothakes-0.0.3.dist-info/WHEEL
mothakes-0.0.3.dist-info/top_level.txt
mothakes-0.0.3.dist-info/RECORD
