Metadata-Version: 2.1
Name: mothakes
Version: 0.0.3
Summary: Tools used by Simon
Home-page: https://github.com/simonfong6/mothakes-python
Author: Simon Fong
Author-email: simonfong6@gmail.com
License: UNKNOWN
Platform: UNKNOWN
Classifier: Programming Language :: Python :: 3
Classifier: License :: OSI Approved :: MIT License
Classifier: Operating System :: OS Independent
Requires-Python: >=3.6
